lapa_authentication/__init__.py
lapa_authentication/configuration.py
lapa_authentication/main.py
lapa_authentication/data/config.ini
lapa_authentication/pydantic_models/__init__.py
lapa_authentication/pydantic_models/pydantic_models.py
lapa_authentication/routes/__init__.py
lapa_authentication/routes/core.py
lapa_authentication/routes/utility.py
lapa_authentication/utils/__init__.py
lapa_authentication/utils/encryption.py
lapa_authentication/utils/token.py
lapa_authentication-0.0.20.dist-info/METADATA
lapa_authentication-0.0.20.dist-info/WHEEL
lapa_authentication-0.0.20.dist-info/top_level.txt
lapa_authentication-0.0.20.dist-info/RECORD
