Metadata-Version: 2.1
Name: lapa-authentication
Version: 0.0.20
Summary: authentication service for my personal server.
Home-page: https://github.com/B21amish/lapa_authentication
Author: Lav Sharma, thePmSquare
Author-email: lavsharma2016@gmail.com, thepmsquare@gmail.com
License: UNKNOWN
Platform: UNKNOWN
Classifier: Development Status :: 3 - Alpha
Classifier: Intended Audience :: Developers
Classifier: License :: OSI Approved :: MIT License
Classifier: Programming Language :: Python :: 3
Classifier: Programming Language :: Python :: 3.9
Requires-Dist: uvicorn >=0.24.0.post1
Requires-Dist: fastapi >=0.104.1
Requires-Dist: pydantic >=2.5.3
Requires-Dist: bcrypt >=4.1.2
Requires-Dist: pyjwt >=2.8.0
Requires-Dist: requests >=2.32.3
Requires-Dist: cryptography >=42.0.7
Requires-Dist: lapa-commons >=0.0.1
Requires-Dist: square-logger >=1.0.0
Requires-Dist: lapa-database-helper >=0.0.5
Requires-Dist: lapa-database-structure >=0.0.11
